[
    {
        "date": "19 Oct 2021",
        "news": "Alpha version. Can create cat. Cat can live. Fixed creating form and some animation bugs."
    },
    {
        "date": "20 Oct 2021",
        "news": "Planed features to the future. Cat can eat and die. Added toilet with clean and getShit methods. Cat can poop."
    },
    {
        "date": "21 Oct 2021",
        "news": "Added carousel. Now can choose cat from the carousel."
    },
    {
        "date": "22 Oct 2021",
        "news": "Fixed bug with an audio and a gif. Added feature when toilet is using, then show gif with a dig animation, while audio is playing. Added button What is new?"
    }
]
